rectanglecropper/__init__.py
rectanglecropper/crop.py
RectangleCropper-1.0.0.dist-info/LICENSE
RectangleCropper-1.0.0.dist-info/METADATA
RectangleCropper-1.0.0.dist-info/WHEEL
RectangleCropper-1.0.0.dist-info/top_level.txt
RectangleCropper-1.0.0.dist-info/RECORD
