Metadata-Version: 2.1
Name: RectangleCropper
Version: 1.0.0
Summary: Crop image to rectangle
Home-page: https://github.com/leeshinyook/RectangleCropper
Author: Shinyook Lee <tlsdbr97@gmail.com>
Author-email: tlsdbr97@gmail.com
License: MIT
Platform: UNKNOWN
Classifier: Programming Language :: Python :: 3
Classifier: License :: OSI Approved :: MIT License
Classifier: Operating System :: OS Independent
Requires-Python: >=3
Requires-Dist: Pillow (==8.3.1)
Requires-Dist: numpy (~=1.21.2)
